pycave/__init__.py
pycave/bayes/__init__.py
pycave/bayes/core/__init__.py
pycave/bayes/core/_jit.py
pycave/bayes/core/normal.py
pycave/bayes/core/types.py
pycave/bayes/core/utils.py
pycave/bayes/gmm/__init__.py
pycave/bayes/gmm/estimator.py
pycave/bayes/gmm/lightning_module.py
pycave/bayes/gmm/metrics.py
pycave/bayes/gmm/model.py
pycave/bayes/gmm/types.py
pycave/bayes/markov_chain/__init__.py
pycave/bayes/markov_chain/estimator.py
pycave/bayes/markov_chain/lightning_module.py
pycave/bayes/markov_chain/metrics.py
pycave/bayes/markov_chain/model.py
pycave/bayes/markov_chain/types.py
pycave/clustering/__init__.py
pycave/clustering/kmeans/__init__.py
pycave/clustering/kmeans/estimator.py
pycave/clustering/kmeans/lightning_module.py
pycave/clustering/kmeans/metrics.py
pycave/clustering/kmeans/model.py
pycave/clustering/kmeans/types.py
pycave/py.typed
pycave/utils/__init__.py
pycave/utils/lightning_module.py
pycave-3.2.1.dist-info/METADATA
pycave-3.2.1.dist-info/LICENSE
pycave-3.2.1.dist-info/WHEEL
pycave-3.2.1.dist-info/RECORD
