Metadata-Version: 2.1
Name: pycave
Version: 3.2.1
Summary: Traditional Machine Learning Models in PyTorch.
Home-page: https://github.com/borchero/pycave
License: MIT
Author: Oliver Borchert
Author-email: me@borchero.com
Requires-Python: >=3.8,<3.11
Classifier: Development Status :: 5 - Production/Stable
Classifier: License :: OSI Approved :: MIT License
Classifier: Programming Language :: Python :: 3
Classifier: Programming Language :: Python :: 3.8
Classifier: Programming Language :: Python :: 3.9
Classifier: Programming Language :: Python :: 3.10
Classifier: Topic :: Scientific/Engineering :: Artificial Intelligence
Requires-Dist: lightkit (>=0.5.0,<0.6.0)
Requires-Dist: numpy (>=1.20.3,<2.0.0)
Requires-Dist: pytorch-lightning (>=1.6.0,<2.0.0)
Requires-Dist: torch (>=1.8.0,<2.0.0)
Requires-Dist: torchmetrics (>=0.6,<0.12)
Project-URL: Documentation, https://pycave.borchero.com
Project-URL: Repository, https://github.com/borchero/pycave
